pypst/__init__.py
pypst/cell.py
pypst/content.py
pypst/document.py
pypst/figure.py
pypst/functional.py
pypst/heading.py
pypst/image.py
pypst/itemize.py
pypst/py.typed
pypst/renderable.py
pypst/set_rule.py
pypst/show_rule.py
pypst/table.py
pypst/utils.py
pypst-0.8.0.dist-info/LICENSE
pypst-0.8.0.dist-info/METADATA
pypst-0.8.0.dist-info/WHEEL
pypst-0.8.0.dist-info/RECORD
