Metadata-Version: 2.1
Name: pypst
Version: 0.8.0
Summary: Declarative Typst in Python with Pandas data frame support.
Home-page: https://github.com/tilman151/pypst
Author: Tilman Krokotsch
Author-email: tilman@krokotsch.eu
Requires-Python: >=3.10,<4.0
Classifier: Development Status :: 3 - Alpha
Classifier: License :: OSI Approved :: MIT License
Classifier: Operating System :: OS Independent
Classifier: Programming Language :: Python :: 3
Classifier: Programming Language :: Python :: 3.10
Classifier: Programming Language :: Python :: 3.11
Classifier: Programming Language :: Python :: 3.12
Classifier: Topic :: Scientific/Engineering
Classifier: Topic :: Text Processing :: Markup
Classifier: Typing :: Typed
Provides-Extra: pandas
Requires-Dist: frozendict (>=2.4.4,<3.0.0)
Requires-Dist: frozenlist (>=1.4.1,<2.0.0)
Requires-Dist: pandas (>=2.2.2,<3.0.0) ; extra == "pandas"
Project-URL: Repository, https://github.com/tilman151/pypst
